neonmoon/__init__.py
neonmoon/neonmoon.py
neonmoon-0.0.1.dist-info/licenses/LICENSE.txt
neonmoon-0.0.1.dist-info/METADATA
neonmoon-0.0.1.dist-info/WHEEL
neonmoon-0.0.1.dist-info/top_level.txt
neonmoon-0.0.1.dist-info/RECORD
