Metadata-Version: 2.4
Name: neonmoon
Version: 0.0.1
Summary: DESCRIPTION
Author-email: Dr Anna Sung and Prof Kelvin Leong <k.leong@chester.ac.uk>
License: BSD-3-Clause
Keywords: stat test,ANOVA,Chi-Square,T-Test
Classifier: Programming Language :: Python :: 3
Classifier: License :: OSI Approved :: MIT License
Classifier: Operating System :: OS Independent
Requires-Python: >=3.8
License-File: LICENSE.txt
Requires-Dist: mlxtend
Requires-Dist: pandas
Requires-Dist: openpyxl
Requires-Dist: scikit-learn
Requires-Dist: matplotlib
Requires-Dist: statsmodels
Dynamic: license-file
